azure/mgmt/playwrighttesting/__init__.py
azure/mgmt/playwrighttesting/_client.py
azure/mgmt/playwrighttesting/_configuration.py
azure/mgmt/playwrighttesting/_model_base.py
azure/mgmt/playwrighttesting/_patch.py
azure/mgmt/playwrighttesting/_serialization.py
azure/mgmt/playwrighttesting/_version.py
azure/mgmt/playwrighttesting/py.typed
azure/mgmt/playwrighttesting/aio/__init__.py
azure/mgmt/playwrighttesting/aio/_client.py
azure/mgmt/playwrighttesting/aio/_configuration.py
azure/mgmt/playwrighttesting/aio/_patch.py
azure/mgmt/playwrighttesting/aio/operations/__init__.py
azure/mgmt/playwrighttesting/aio/operations/_operations.py
azure/mgmt/playwrighttesting/aio/operations/_patch.py
azure/mgmt/playwrighttesting/models/__init__.py
azure/mgmt/playwrighttesting/models/_enums.py
azure/mgmt/playwrighttesting/models/_models.py
azure/mgmt/playwrighttesting/models/_patch.py
azure/mgmt/playwrighttesting/operations/__init__.py
azure/mgmt/playwrighttesting/operations/_operations.py
azure/mgmt/playwrighttesting/operations/_patch.py
azure_mgmt_playwrighttesting-1.0.1.dist-info/licenses/LICENSE
azure_mgmt_playwrighttesting-1.0.1.dist-info/METADATA
azure_mgmt_playwrighttesting-1.0.1.dist-info/WHEEL
azure_mgmt_playwrighttesting-1.0.1.dist-info/top_level.txt
azure_mgmt_playwrighttesting-1.0.1.dist-info/RECORD
